{"cameraMode":{"drawMode":0,"name":"Shaded","section":"Shading Mode"},"sceneLighting":false,"audioPlay":false,"sceneViewState":{"m_AlwaysRefresh":false,"showFog":true,"showSkybox":false,"showFlares":true,"showImageEffects":true,"showParticleSystems":true,"showVisualEffectGraphs":true,"m_FxEnabled":true},"in2DMode":false,"pivot":{"x":-5.0,"y":3.0,"z":22.382240295410158},"rotation":{"x":0.08428683131933212,"y":-0.8823110461235046,"z":0.4294748604297638,"w":0.1731622964143753},"size":4.1369194984436039,"orthographic":false}